pdfme/__init__.py
pdfme/base.py
pdfme/color.py
pdfme/content.py
pdfme/document.py
pdfme/encoders.py
pdfme/fonts.py
pdfme/image.py
pdfme/page.py
pdfme/parser.py
pdfme/pdf.py
pdfme/table.py
pdfme/text.py
pdfme/utils.py
pdfme-0.5.0.dist-info/licenses/LICENSE
tests/__init__.py
tests/group_element.py
tests/running_section_per_page.py
tests/test_content.py
tests/test_table.py
tests/test_text.py
tests/utils.py
pdfme-0.5.0.dist-info/METADATA
pdfme-0.5.0.dist-info/WHEEL
pdfme-0.5.0.dist-info/top_level.txt
pdfme-0.5.0.dist-info/RECORD
