Metadata-Version: 2.4
Name: pdfme
Version: 0.5.0
Summary: Create PDFs easily
Home-page: https://github.com/aFelipeSP/pdfme
Author: Andrés Felipe Sierra Parra
Author-email: cepfelo@gmail.com
Project-URL: Bug Tracker, https://github.com/aFelipeSP/pdfme/issues
Classifier: Programming Language :: Python :: 3
Classifier: License :: OSI Approved :: MIT License
Classifier: Operating System :: OS Independent
Classifier: Development Status :: 4 - Beta
Classifier: Intended Audience :: Developers
Classifier: Topic :: Software Development :: Libraries :: Python Modules
Classifier: Topic :: Multimedia :: Graphics
Requires-Python: >=3.6
License-File: LICENSE
Dynamic: license-file
